{
  "trainingPhrases": [ {
    "parts": [ {
      "text": "Ano tong encountered device is used by another user?",
      "auto": true
    } ],
    "repeatCount": 1,
    "languageCode": "en"
  }, {
    "parts": [ {
      "text": "Encountered Device is used by another user message",
      "auto": true
    } ],
    "repeatCount": 1,
    "languageCode": "en"
  }, {
    "parts": [ {
      "text": "Device is used by another user appears",
      "auto": true
    } ],
    "repeatCount": 1,
    "languageCode": "en"
  } ]
}
