{
  "trainingPhrases": [ {
    "parts": [ {
      "text": "I cannot remember my password"
    } ],
    "repeatCount": 1,
    "languageCode": "en"
  }, {
    "parts": [ {
      "text": "How do I reset my password?",
      "auto": true
    } ],
    "repeatCount": 1,
    "languageCode": "en"
  }, {
    "parts": [ {
      "text": "What is my password?",
      "auto": true
    } ],
    "repeatCount": 1,
    "languageCode": "en"
  }, {
    "parts": [ {
      "text": "I forgot my password, what can I do to be able to log in?",
      "auto": true
    } ],
    "repeatCount": 1,
    "languageCode": "en"
  } ]
}
